nobinobi_child
