Metadata-Version: 2.1
Name: nobinobi-child
Version: 0.1.4.16
Summary: Application Child for Nobinobi
Home-page: https://github.com/prolibre-ch/nobinobi-child
Author: Florian Alu
Author-email: alu@prolibre.com
License: UNKNOWN
Keywords: nobinobi-child
Platform: UNKNOWN
Classifier: Development Status :: 4 - Beta
Classifier: Framework :: Django :: 3.1
Classifier: Intended Audience :: Developers
Classifier: License :: OSI Approved :: GNU Affero General Public License v3 or later (AGPLv3+)
Classifier: Natural Language :: English
Classifier: Programming Language :: Python :: 3.6
Classifier: Programming Language :: Python :: 3.7
Classifier: Programming Language :: Python :: 3.8
License-File: LICENSE
License-File: AUTHORS.rst
Requires-Dist: nobinobi-staff (>=0.1.6.8)
Requires-Dist: django-phonenumber-field (==7.1.0)
Requires-Dist: phonenumbers (==8.13.21)
Requires-Dist: django-select2 (==8.1.2)
Requires-Dist: django-bootstrap-modal-forms (==3.0.4)
Requires-Dist: django-widget-tweaks (==1.5.0)
Requires-Dist: django-simple-menu (==2.1.2.post1)
Requires-Dist: django-weasyprint (==2.2.1)
